UART/uart_tx.sv
module uart_tx (
    input  logic       clk,
    input  logic       reset,
    input  logic       start,
    input  logic [7:0] data,
    output logic       tx,
    output logic       busy
);

logic [3:0] bit_count;
logic [9:0] frame;

always_ff @(posedge clk) begin
    if (reset) begin
        tx        <= 1'b1;
        busy      <= 1'b0;
        bit_count <= 0;
    end
    else if (start && !busy) begin
        // {stop bit, data, start bit}
        frame     <= {1'b1, data, 1'b0};
        busy      <= 1'b1;
        bit_count <= 0;
    end
    else if (busy) begin
        tx <= frame[bit_count];

        if (bit_count == 9) begin
            busy <= 1'b0;
            tx   <= 1'b1;
        end
        else begin
            bit_count <= bit_count + 1;
        end
    end
end

endmodule

UART/uart_tx_tb.sv
module uart_tx_tb;

logic clk = 0;
logic reset;
logic start;
logic [7:0] data;
logic tx;
logic busy;

uart_tx dut (
    .clk(clk),
    .reset(reset),
    .start(start),
    .data(data),
    .tx(tx),
    .busy(busy)
);

always #5 clk = ~clk;

initial begin
    $dumpfile("uart_tx.vcd");
    $dumpvars(0, uart_tx_tb);

    reset = 1;
    start = 0;
    data  = 0;

    #20;
    reset = 0;

    #10;
    data  = 8'h55;   // 01010101
    start = 1;

    #10;
    start = 0;

    #150;
    $finish;
end

endmodule

UART/uart_tx.vcd
$date
	Tue Sep 15 15:11:15 2026
$end
$version
	Icarus Verilog
$end
$timescale
	1s
$end
$scope module uart_tx_tb $end
$var wire 1 ! tx $end
$var wire 1 " busy $end
$var reg 1 # clk $end
$var reg 8 $ data [7:0] $end
$var reg 1 % reset $end
$var reg 1 & start $end
$scope module dut $end
$var wire 1 # clk $end
$var wire 8 ' data [7:0] $end
$var wire 1 % reset $end
$var wire 1 & start $end
$var reg 4 ( bit_count [3:0] $end
$var reg 1 " busy $end
$var reg 10 ) frame [9:0] $end
$var reg 1 ! tx $end
$upscope $end
$upscope $end
$enddefinitions $end
$comment Show the parameter values. $end
$dumpall
$end
#0
$dumpvars
bx )
bx (
b0 '
0&
1%
b0 $
0#
x"
x!
$end
#5
b0 (
0"
1!
1#
#10
0#
#15
1#
#20
0#
0%
#25
1#
#30
0#
1&
b1010101 $
b1010101 '
#35
1"
b1010101010 )
1#
#40
0#
0&
#45
b1 (
0!
1#
#50
0#
#55
b10 (
1!
1#
#60
0#
#65
b11 (
0!
1#
#70
0#
#75
b100 (
1!
1#
#80
0#
#85
b101 (
0!
1#
#90
0#
#95
b110 (
1!
1#
#100
0#
#105
b111 (
0!
1#
#110
0#
#115
b1000 (
1!
1#
#120
0#
#125
b1001 (
0!
1#
#130
0#
#135
0"
1!
1#
